README.md
setup.py
tweet_scraper_bot/__init__.py
tweet_scraper_bot.egg-info/PKG-INFO
tweet_scraper_bot.egg-info/SOURCES.txt
tweet_scraper_bot.egg-info/dependency_links.txt
tweet_scraper_bot.egg-info/requires.txt
tweet_scraper_bot.egg-info/top_level.txt