Metadata-Version: 2.1
Name: tweet-scraper-bot
Version: 1.0.0
Summary: A python library to scrape tweet data from twitter automatically.
Home-page: https://twitter-api.datakund.com/en/latest/
Author: DataKund
Author-email: datakund@gmail.com
License: Apache License 2.0
Keywords: twitter python bot_studio scraper login tweet data web-scraping
Platform: UNKNOWN
